xacro/__init__.py
xacro/cli.py
xacro/color.py
xacro/substitution_args.py
xacro/xmlutils.py
xacro-2.1.0.dist-info/licenses/LICENSE
xacro-2.1.0.dist-info/METADATA
xacro-2.1.0.dist-info/WHEEL
xacro-2.1.0.dist-info/entry_points.txt
xacro-2.1.0.dist-info/top_level.txt
xacro-2.1.0.dist-info/RECORD
