Metadata-Version: 2.4
Name: xacro
Version: 2.1.0
Summary: xacro is a macro language for XML
License: Copyright Robert Haschke, Bielefeld University
Project-URL: Documentation, https://github.com/ros/xacro/wiki
Project-URL: Repository, https://github.com/ros/xacro
Requires-Python: >=3.8
License-File: LICENSE
Requires-Dist: pyyaml
Dynamic: license-file
